modeltranslation_rosetta/__init__.py
modeltranslation_rosetta/admin.py
modeltranslation_rosetta/admin_views.py
modeltranslation_rosetta/apps.py
modeltranslation_rosetta/compat.py
modeltranslation_rosetta/custom_admin.py
modeltranslation_rosetta/export_translation.py
modeltranslation_rosetta/filter.py
modeltranslation_rosetta/forms.py
modeltranslation_rosetta/import_translation.py
modeltranslation_rosetta/models.py
modeltranslation_rosetta/settings.py
modeltranslation_rosetta/templates.py
modeltranslation_rosetta/view_mixins.py
modeltranslation_rosetta/views.py
modeltranslation_rosetta/management/__init__.py
modeltranslation_rosetta/management/commands/__init__.py
modeltranslation_rosetta/management/commands/_utils.py
modeltranslation_rosetta/management/commands/export_translation.py
modeltranslation_rosetta/management/commands/import_translation.py
modeltranslation_rosetta/migrations/0001_add_permissions.py
modeltranslation_rosetta/migrations/__init__.py
modeltranslation_rosetta/static/modeltranslation_rosetta/js/app.js
modeltranslation_rosetta/templates/modeltranslation_rosetta/default/base.html
modeltranslation_rosetta/templates/modeltranslation_rosetta/default/edit_translation.html
modeltranslation_rosetta/templates/modeltranslation_rosetta/default/import.html
modeltranslation_rosetta/templates/modeltranslation_rosetta/default/list_models.html
modeltranslation_rosetta/templatetags/__init__.py
modeltranslation_rosetta/templatetags/modeltranslation_rosetta.py
modeltranslation_rosetta/utils/__init__.py
modeltranslation_rosetta/utils/response.py
modeltranslation_rosetta/utils/signals.py
modeltranslation_rosetta/utils/utils.py
modeltranslation_rosetta/utils/xml/__init__.py
modeltranslation_rosetta/utils/xml/parse.py
modeltranslation_rosetta/utils/xml/render.py
modeltranslation_rosetta/utils/xml/tests/__init__.py
modeltranslation_rosetta/utils/xml/tests/test_xml.py
django_modeltranslation_rosetta-0.0.8.dist-info/LICENSE
django_modeltranslation_rosetta-0.0.8.dist-info/METADATA
django_modeltranslation_rosetta-0.0.8.dist-info/WHEEL
django_modeltranslation_rosetta-0.0.8.dist-info/top_level.txt
django_modeltranslation_rosetta-0.0.8.dist-info/RECORD
